phmdoctest/__init__.py
phmdoctest/__main__.py
phmdoctest/cases.py
phmdoctest/direct.py
phmdoctest/entryargs.py
phmdoctest/fenced.py
phmdoctest/fillrole.py
phmdoctest/fixture.py
phmdoctest/functions.py
phmdoctest/inline.py
phmdoctest/main.py
phmdoctest/py.typed
phmdoctest/report.py
phmdoctest/simulator.py
phmdoctest/tester.py
phmdoctest/tool.py
phmdoctest/using.py
phmdoctest-1.4.0.dist-info/LICENSE.txt
phmdoctest-1.4.0.dist-info/METADATA
phmdoctest-1.4.0.dist-info/WHEEL
phmdoctest-1.4.0.dist-info/entry_points.txt
phmdoctest-1.4.0.dist-info/top_level.txt
phmdoctest-1.4.0.dist-info/RECORD
