Metadata-Version: 2.1
Name: phmdoctest
Version: 1.4.0
Summary: Python syntax highlighted Markdown doctest.
Home-page: https://tmarktaylor.github.io/phmdoctest
Author: Mark Taylor
Author-email: mark66547ta2@gmail.com
License: MIT
Project-URL: Bug Reports, https://github.com/tmarktaylor/phmdoctest/issues
Project-URL: Source, https://github.com/tmarktaylor/phmdoctest/
Keywords: documentation,doctest,markdown,testing
Platform: UNKNOWN
Classifier: Development Status :: 4 - Beta
Classifier: Intended Audience :: Developers
Classifier: Topic :: Software Development :: Testing
Classifier: Topic :: Software Development :: Documentation
Classifier: Topic :: Software Development :: Libraries :: Python Modules
Classifier: Topic :: Utilities
Classifier: License :: OSI Approved :: MIT License
Classifier: Programming Language :: Python :: 3 :: Only
Classifier: Programming Language :: Python :: 3.7
Classifier: Programming Language :: Python :: 3.8
Classifier: Programming Language :: Python :: 3.9
Classifier: Programming Language :: Python :: 3.10
Classifier: Programming Language :: Python :: Implementation :: PyPy
Requires-Python: >=3.6
License-File: LICENSE.txt
Requires-Dist: pytest
Requires-Dist: Click (>=7.1.1)
Requires-Dist: commonmark (>=0.9.1)
Requires-Dist: monotable (>=2.1.1)
Requires-Dist: tomli (>=1.0.0) ; python_version < "3.11"
Provides-Extra: docs
Requires-Dist: myst-parser ; extra == 'docs'
Requires-Dist: sphinx ; extra == 'docs'
Requires-Dist: sphinx-rtd-theme ; extra == 'docs'
Provides-Extra: inspect
Requires-Dist: black ; extra == 'inspect'
Requires-Dist: flake8 ; extra == 'inspect'
Requires-Dist: pep8-naming ; extra == 'inspect'
Requires-Dist: mypy ; extra == 'inspect'
Requires-Dist: typing ; extra == 'inspect'
Requires-Dist: check-manifest ; extra == 'inspect'
Requires-Dist: twine ; extra == 'inspect'
Provides-Extra: test
Requires-Dist: coverage ; extra == 'test'
Requires-Dist: pytest (>=6.2) ; extra == 'test'
Requires-Dist: PyYAML (>=5.4.1) ; extra == 'test'
